{
  "title": "Changelog: v1.4.0",
  "summary": "Performance improvements, bug fixes, and dependency updates.",
  "attributes": {
    "version": "1.4.0",
    "date": "2025-08-17",
    "added": "Incremental indexing; new health endpoint",
    "changed": "~25% faster search; streamlined logging",
    "fixed": "Race condition in scheduler; pagination bug",
    "deprecated": "Legacy v1 auth slated for removal in v1.6",
    "removed": "None"
  },
  "metadata": {
    "token": "91a7fd3a",
    "commit": "c3e4b1d",
    "author": "release-bot",
    "component": "search-service",
    "env": "production",
    "created_at": "2025-08-17T12:00:00Z"
  }
}