{
  "title": "Changelog: v1.2.3",
  "summary": "Bug fixes, performance improvements, and minor features.",
  "attributes": {
    "version": "1.2.3",
    "date": "2025-08-15",
    "changes": "Fix auth retry bug; optimize cache; add metrics endpoint",
    "breaking": "none",
    "issue_refs": "#124,#130,#141",
    "commit_count": "7",
    "authors": "alice,bob"
  },
  "metadata": {
    "release_id": "rel-20250815-1",
    "service": "billing-api",
    "env": "production",
    "build_number": "20250815.1",
    "token": "29a91ace",
    "created_at": "2025-08-15T12:00:00Z"
  }
}